a3cosmos_gas_evolution/__init__.py
a3cosmos_gas_evolution/__main__.py
a3cosmos_gas_evolution/Common_Python_Code/__init__.py
a3cosmos_gas_evolution/Common_Python_Code/apply_cosmology.py
a3cosmos_gas_evolution/Common_Python_Code/calc_alpha_CO.py
a3cosmos_gas_evolution/Common_Python_Code/calc_alpha_RJ.py
a3cosmos_gas_evolution/Common_Python_Code/calc_cosmic_comoving_volume.py
a3cosmos_gas_evolution/Common_Python_Code/calc_cosmic_star_formation_rate_density.py
a3cosmos_gas_evolution/Common_Python_Code/calc_delta_GD.py
a3cosmos_gas_evolution/Common_Python_Code/calc_dust_opacity_kappa.py
a3cosmos_gas_evolution/Common_Python_Code/calc_dust_planck_law.py
a3cosmos_gas_evolution/Common_Python_Code/calc_dust_rayleigh_jeans_law.py
a3cosmos_gas_evolution/Common_Python_Code/calc_fmol.py
a3cosmos_gas_evolution/Common_Python_Code/calc_galaxy_dust_obscuration.py
a3cosmos_gas_evolution/Common_Python_Code/calc_galaxy_gas_mass_function.py
a3cosmos_gas_evolution/Common_Python_Code/calc_galaxy_luminosity_function.py
a3cosmos_gas_evolution/Common_Python_Code/calc_galaxy_main_sequence.py
a3cosmos_gas_evolution/Common_Python_Code/calc_galaxy_size_evolution.py
a3cosmos_gas_evolution/Common_Python_Code/calc_galaxy_stellar_mass_function.py
a3cosmos_gas_evolution/Common_Python_Code/calc_gas_depletion_time.py
a3cosmos_gas_evolution/Common_Python_Code/calc_gas_fraction.py
a3cosmos_gas_evolution/Common_Python_Code/calc_gas_mass_from_dust.py
a3cosmos_gas_evolution/Common_Python_Code/calc_metal_Z.py
a3cosmos_gas_evolution/Common_Python_Code/calc_planck_law.py
a3cosmos_gas_evolution/Common_Python_Code/calc_star_formation_law.py
a3cosmos_gas_evolution/Common_Python_Code/catalog_cross_matching.py
a3cosmos_gas_evolution/Common_Python_Code/get_cosmic_mol_gas_density.py
a3cosmos_gas_evolution/Common_Python_Code/read_z_Mstar_SFR_Mgas_datasets.py
a3cosmos_gas_evolution/Common_Python_Code/setup_matplotlib.py
a3cosmos_gas_evolution/Common_Python_Code/__pycache__/apply_cosmology.cpython-37.pyc
a3cosmos_gas_evolution-1.1.1.dist-info/AUTHORS.txt
a3cosmos_gas_evolution-1.1.1.dist-info/LICENSE.txt
a3cosmos_gas_evolution-1.1.1.dist-info/METADATA
a3cosmos_gas_evolution-1.1.1.dist-info/WHEEL
a3cosmos_gas_evolution-1.1.1.dist-info/top_level.txt
a3cosmos_gas_evolution-1.1.1.dist-info/RECORD
