Metadata-Version: 2.1
Name: a3cosmos-gas-evolution
Version: 1.1.1
Summary: A Python Package for Galaxy Cold Molecular Gas and Star Formation Evolution Equations.
Home-page: https://sites.google.com/view/a3cosmos
Author: A3COSMOS Team
Author-email: dzliu@mpe.mpg.de
Maintainer: A3COSMOS Team
Maintainer-email: dzliu@mpe.mpg.de
License: BSD License
Project-URL: Documentation, https://sites.google.com/view/a3cosmos/code/code-a3cosmos-gas-evolution
Project-URL: Source Code, https://github.com/1054/a3cosmos-gas-evolution
Keywords: a3cosmos galaxy molecular gas dust star formation SFR evolution equation parametrization
Platform: all
Classifier: Development Status :: 4 - Beta
Classifier: Development Status :: 5 - Production/Stable
Classifier: Operating System :: OS Independent
Classifier: Intended Audience :: Developers
Classifier: License :: OSI Approved :: ISC License (ISCL)
Classifier: Programming Language :: Python
Classifier: Programming Language :: Python :: Implementation
Classifier: Programming Language :: Python :: 2
Classifier: Programming Language :: Python :: 2.7
Classifier: Programming Language :: Python :: 3
Classifier: Programming Language :: Python :: 3.4
Classifier: Programming Language :: Python :: 3.5
Classifier: Programming Language :: Python :: 3.6
Classifier: Programming Language :: Python :: 3.7
Classifier: Programming Language :: Python :: 3.8
Classifier: Programming Language :: Python :: 3.9
Classifier: Topic :: Scientific/Engineering :: Astronomy
Requires-Dist: numpy
Requires-Dist: astropy
Requires-Dist: scipy
Requires-Dist: matplotlib
Requires-Dist: funcsigs ; python_version < "3.0"
